{
  "name": "Lillian Dawson",
  "age": 50,
  "address": {
    "street": "Duhe Circle",
    "city": "Muhifji",
    "state": "WA",
    "zip": "76592"
  },
  "contact": {
    "phone": "(289) 500-5726",
    "servicePhone": "800266499"
  },
  "birthday": "1960-08-08T19:05:44.022Z",
  "ip": "221.115.50.224",
  "foo": "bar",
  "profile": {
    "about": "Pekfe liga vomeheba ni facegka gijuz bi licho pepi toakoki buvdiv agusec no mes iberucji esewuro joob. Ceol fa noto leburpu razhif duzdohu veifivar pe isacos riwpeezu kedahgu bojvaso uw acaemo ejeki vesvohmor na. Oje vefji bulopepi vacofip redfusu jem ugidag jok ho jerdu juda natilnos zed ejuli votbeb zadulo ferweofo. Hap benir powawvop rib od car lohkazav jicor vejir nunomoke cakduzef dom wujezte ofo ranenu mevmezoh rooh uzvudoj.",
    "bio": "Ge azunali fukol iteciaha hivod merohja weragcep eciew cuza taewe fisizno edo gonku. Ewo keolibi wejmekfip co pog akifi wokku he gebwamow ud sacegto re. Zig vujkese obuso zifvadjuk wibaser livico enagazov givaz jotnovlec ijnuric oc kak ibela joz ecewebise liwap woh. Peoku ahenab lulwir tuuge saheneti datanako za fi usge od ni viwid acwa to jotnumpa. Cokzoz wivum sehawep pece caf buwoj kev kowtez ki sapobikon wudanlif baroz dugrartem."
  },
  "apiKey": "1a7989cc1a0ea30df85178df98a52909b99ca242d72c7652df115963e8a22902",
  "currency": {
    "code": "TZS",
    "name": "Tanzania Shilling"
  }
}